starlette_feedgen/__init__.py
starlette_feedgen/feed.py
starlette_feedgen/generator.py
starlette_feedgen/utils.py
starlette_feedgen-0.1.4.dist-info/LICENSE
starlette_feedgen-0.1.4.dist-info/WHEEL
starlette_feedgen-0.1.4.dist-info/METADATA
starlette_feedgen-0.1.4.dist-info/RECORD
