Metadata-Version: 2.1
Name: starlette-feedgen
Version: 0.1.4
Summary: Asynchronous RSS/Atom feeds generation for Starlette, adapted from Django syndication feed framework.
Home-page: https://github.com/tinkoffjournal/starlette-feedgen
License: MIT
Author: Arseny Gabdullin
Author-email: a.gabdullin@tinkoff.ru
Maintainer: Andrey Tsvetkov
Maintainer-email: an.a.tsvetkov@tinkoff.ru
Requires-Python: >=3.10,<4.0
Classifier: Environment :: Web Environment
Classifier: Intended Audience :: Developers
Classifier: License :: OSI Approved :: MIT License
Classifier: Operating System :: OS Independent
Classifier: Programming Language :: Python :: 3
Classifier: Programming Language :: Python :: 3.10
Classifier: Programming Language :: Python :: 3.11
Classifier: Programming Language :: Python :: 3
Classifier: Programming Language :: Python :: 3.10
Classifier: Topic :: Internet :: WWW/HTTP
Requires-Dist: aiofiles (>=22.1.0,<23.0.0)
Requires-Dist: starlette (>=0.21.0,<0.22.0)
Project-URL: Repository, https://github.com/tinkoffjournal/starlette-feedgen
